mmlearn/__init__.py
mmlearn/constants.py
mmlearn/hf_utils.py
mmlearn/cli/__init__.py
mmlearn/cli/_instantiators.py
mmlearn/cli/run.py
mmlearn/conf/__init__.py
mmlearn/datasets/__init__.py
mmlearn/datasets/chexpert.py
mmlearn/datasets/imagenet.py
mmlearn/datasets/librispeech.py
mmlearn/datasets/llvip.py
mmlearn/datasets/nihcxr.py
mmlearn/datasets/nyuv2.py
mmlearn/datasets/sunrgbd.py
mmlearn/datasets/core/__init__.py
mmlearn/datasets/core/combined_dataset.py
mmlearn/datasets/core/data_collator.py
mmlearn/datasets/core/example.py
mmlearn/datasets/core/modalities.py
mmlearn/datasets/core/samplers.py
mmlearn/datasets/processors/__init__.py
mmlearn/datasets/processors/masking.py
mmlearn/datasets/processors/tokenizers.py
mmlearn/datasets/processors/transforms.py
mmlearn/modules/__init__.py
mmlearn/modules/ema.py
mmlearn/modules/encoders/__init__.py
mmlearn/modules/encoders/clip.py
mmlearn/modules/encoders/text.py
mmlearn/modules/encoders/vision.py
mmlearn/modules/layers/__init__.py
mmlearn/modules/layers/attention.py
mmlearn/modules/layers/embedding.py
mmlearn/modules/layers/logit_scaling.py
mmlearn/modules/layers/mlp.py
mmlearn/modules/layers/normalization.py
mmlearn/modules/layers/patch_dropout.py
mmlearn/modules/layers/transformer_block.py
mmlearn/modules/losses/__init__.py
mmlearn/modules/losses/contrastive.py
mmlearn/modules/losses/data2vec.py
mmlearn/modules/lr_schedulers/__init__.py
mmlearn/modules/lr_schedulers/linear_warmup_cosine_lr.py
mmlearn/modules/metrics/__init__.py
mmlearn/modules/metrics/retrieval_recall.py
mmlearn/tasks/__init__.py
mmlearn/tasks/base.py
mmlearn/tasks/contrastive_pretraining.py
mmlearn/tasks/hooks.py
mmlearn/tasks/ijepa.py
mmlearn/tasks/zero_shot_classification.py
mmlearn/tasks/zero_shot_retrieval.py
mmlearn-0.1.0b2.dist-info/METADATA
mmlearn-0.1.0b2.dist-info/WHEEL
mmlearn-0.1.0b2.dist-info/entry_points.txt
mmlearn-0.1.0b2.dist-info/licenses/LICENSE
mmlearn-0.1.0b2.dist-info/RECORD
