Metadata-Version: 2.4
Name: mmlearn
Version: 0.1.0b2
Summary: A modular framework for research on multimodal representation learning.
Author-email: Vector AI Engineering <ai_engineering@vectorinstitute.ai>
License-Expression: Apache-2.0
License-File: LICENSE
Requires-Python: <3.13,>=3.10
Requires-Dist: bottleneck<2.0.0,>=1.4.2
Requires-Dist: hydra-core<2.0.0,>=1.3.2
Requires-Dist: hydra-submitit-launcher<2.0.0,>=1.2.0
Requires-Dist: hydra-zen<0.14.0,>=0.13.0
Requires-Dist: lightning<3.0.0,>=2.5.0.post0
Requires-Dist: numpy<2.0.0,>=1.26.4
Requires-Dist: pandas<3.0.0,>=2.2.3; extra == 'performance'
Requires-Dist: pyarrow<18.0.0,>=17.0.0
Requires-Dist: torch<2.6.0,>=2.5.1
Requires-Dist: torchvision<0.21.0,>=0.20.1
Requires-Dist: transformers<5.0.0,>=4.48.3
Provides-Extra: audio
Requires-Dist: torchaudio<2.6.0,>=2.5.1; extra == 'audio'
Provides-Extra: peft
Requires-Dist: peft<0.15.0,>=0.14.0; extra == 'peft'
Provides-Extra: vision
Requires-Dist: opencv-python<5.0.0,>=4.11.0.86; extra == 'vision'
Requires-Dist: timm<2.0.0,>=1.0.14; extra == 'vision'
